siya_yahoo_finance_mcp/__init__.py
siya_yahoo_finance_mcp/server.py
siya_yahoo_finance_mcp-0.1.2.dist-info/METADATA
siya_yahoo_finance_mcp-0.1.2.dist-info/WHEEL
siya_yahoo_finance_mcp-0.1.2.dist-info/entry_points.txt
siya_yahoo_finance_mcp-0.1.2.dist-info/licenses/LICENSE
siya_yahoo_finance_mcp-0.1.2.dist-info/RECORD
