Metadata-Version: 2.4
Name: siya-yahoo-finance-mcp
Version: 0.1.2
Summary: MCP server implementation for yahoo finance integration
Project-URL: Homepage, https://github.com/Alex2Yang97/yahoo-finance-mcp
Project-URL: Repository, https://github.com/Alex2Yang97/yahoo-finance-mcp
Project-URL: Issues, https://github.com/Alex2Yang97/yahoo-finance-mcp/issues
Author-email: Siya AI <contact@siya.ai>
License: MIT License
License-File: LICENSE
Keywords: ai,claude,financial-data,mcp,yahoo-finance
Classifier: Development Status :: 4 - Beta
Classifier: Intended Audience :: Developers
Classifier: License :: OSI Approved :: MIT License
Classifier: Operating System :: OS Independent
Classifier: Programming Language :: Python :: 3
Classifier: Programming Language :: Python :: 3.11
Classifier: Programming Language :: Python :: 3.12
Classifier: Topic :: Office/Business :: Financial
Classifier: Topic :: Software Development :: Libraries :: Python Modules
Requires-Python: >=3.12
Requires-Dist: mcp[cli]>=1.6.0
Requires-Dist: yfinance>=0.2.62
Provides-Extra: dev
Requires-Dist: black>=24.2.0; extra == 'dev'
Requires-Dist: isort>=5.13.2; extra == 'dev'
Requires-Dist: pre-commit>=3.6.0; extra == 'dev'
